designs/rtl/lif_acc/LIF_acceleralor_254/sverilog/Neuromorphic_design.svh
// ===========================================================
// RTL generated by ActiveCore framework
// Date: 2024-09-28 21:29:54
// Copyright Alexander Antonov <antonov.alex.alex@gmail.com>
// ===========================================================

`ifndef __Neuromorphic_design_h_
`define __Neuromorphic_design_h_

`endif // __Neuromorphic_design_h_

designs/rtl/lif_acc/LIF_acceleralor_256_256_4/sverilog/Neuromorphic_design.sv
// ===========================================================
// RTL generated by ActiveCore framework
// Date: 2024-09-28 15:42:31
// Copyright Alexander Antonov <antonov.alex.alex@gmail.com>
// ===========================================================

`include "Neuromorphic_design.svh"

module Neuromorphic_design (
	input logic unsigned [0:0] clk_i
	, input logic unsigned [0:0] rst_i
);


logic unsigned [31:0] tick;
logic unsigned [31:0] tick_period;
logic unsigned [31:0] clk_counter;
logic unsigned [31:0] next_clk_count;
logic unsigned [31:0] input_spike;
logic unsigned [0:0] gen4_cyclix_genvar;
logic unsigned [0:0] gen5_cyclix_genvar;
logic unsigned [32:0] gen6_cyclix_genvar;
logic unsigned [0:0] gen7_cyclix_genvar;
logic unsigned [0:0] gen0_rtl_var;
logic unsigned [0:0] gen1_rtl_var;

logic unsigned [31:0] gensticky_tick;
always_ff @(posedge clk_i)
	if (rst_i)
		begin
		gensticky_tick <= 32'd0;
		end
	else
		begin
		gensticky_tick <= tick;
		end

logic unsigned [31:0] gensticky_tick_period;
always_ff @(posedge clk_i)
	if (rst_i)
		begin
		gensticky_tick_period <= 32'd5;
		end
	else
		begin
		gensticky_tick_period <= tick_period;
		end

logic unsigned [31:0] gensticky_clk_counter;
always_ff @(posedge clk_i)
	if (rst_i)
		begin
		gensticky_clk_counter <= 32'd0;
		end
	else
		begin
		gensticky_clk_counter <= clk_counter;
		end

logic unsigned [31:0] gensticky_next_clk_count;
always_ff @(posedge clk_i)
	if (rst_i)
		begin
		gensticky_next_clk_count <= 32'd0;
		end
	else
		begin
		gensticky_next_clk_count <= next_clk_count;
		end

logic unsigned [31:0] gensticky_input_spike;
always_ff @(posedge clk_i)
	if (rst_i)
		begin
		gensticky_input_spike <= 32'd0;
		end
	else
		begin
		gensticky_input_spike <= input_spike;
		end


always_comb
	begin
	tick = 32'd0;
	gen6_cyclix_genvar = 32'd0;
	next_clk_count = 32'd0;
	clk_counter = 32'd0;
	tick_period = gensticky_tick_period;
	tick = gensticky_tick;
	next_clk_count = gensticky_next_clk_count;
	clk_counter = gensticky_clk_counter;
	input_spike = gensticky_input_spike;
	// Buffering globals
	// Processing dlychains
	// fifo_in buffering
	// subproc fifo_in buffering
	// Payload logic
	tick_period = 32'd5;
	gen4_cyclix_genvar = (tick_period != clk_counter);
	gen5_cyclix_genvar = gen4_cyclix_genvar;
	gen0_rtl_var = gen5_cyclix_genvar;
	if (gen0_rtl_var)
		begin
		tick = 32'd0;
		gen6_cyclix_genvar = (clk_counter + 32'd1);
		next_clk_count = gen6_cyclix_genvar;
		clk_counter = next_clk_count;
		end
	gen7_cyclix_genvar = 1'd0;
	gen7_cyclix_genvar = (gen7_cyclix_genvar || gen5_cyclix_genvar);
	gen7_cyclix_genvar = !gen7_cyclix_genvar;
	gen1_rtl_var = gen7_cyclix_genvar;
	if (gen1_rtl_var)
		begin
		tick = 32'd1;
		clk_counter = 32'd0;
		end
	input_spike = 32'd1;
	end


endmodule

designs/rtl/lif_acc/LIF_acceleralor_256_256_4/sverilog/tb_tick.sv
`timescale 1ns/1ps

module Neuromorphic_design_tb;

  // Порты для подключения к тестируемому модулю
  logic unsigned [0:0] clk_i;
  logic unsigned [0:0] rst_i;

  // Параметры для симуляции
  parameter CLK_PERIOD = 10; // Период тактового сигнала 10 нс

  // Экземпляр тестируемого модуля
  Neuromorphic_design uut (
    .clk_i(clk_i),
    .rst_i(rst_i)
  );

  // Генерация тактового сигнала
  always #(CLK_PERIOD / 2) clk_i = ~clk_i;

  // Процесс инициализации и тестирования
  initial begin
    // Инициализация сигналов
    clk_i = 0;
    rst_i = 1;

    // Открываем файл для VCD
    $dumpfile("Neuromorphic_design_tb.vcd");
    $dumpvars(0, Neuromorphic_design_tb);
    $dumpvars(0, uut);



    // Старт тестирования
    #20; // Задержка для начальной стабилизации

    // Сброс системы
    rst_i = 0;
    #100;
    
    // Поднимаем сигнал сброса для перезапуска
    rst_i = 1;
    #20;
    rst_i = 0;

    // Наблюдаем за сигналами некоторое время
    #50000;

    // Завершение симуляции
    $finish;
  end

  // Отслеживание сигналов в консоли
  always @(posedge clk_i) begin
    // $display("Time: %0t | tick: %0d, tick_period: %0d, clk_counter: %0d, next_clk_count: %0d, input_spike: %0d",
    //          $time, tick, tick_period, clk_counter, next_clk_count, input_spike);
  end

endmodule

designs/rtl/lif_acc/LIF_acceleralor_254/sverilog/Neuromorphic_design_tb.vcd
$date
	Sat Sep 28 16:16:26 2024
$end
$version
	Icarus Verilog
$end
$timescale
	1ps
$end
$scope module Neuromorphic_design_tb $end
$var reg 1 ! clk_i $end
$var reg 1 " rst_i $end
$scope module uut $end
$var wire 1 ! clk_i $end
$var wire 1 " rst_i $end
$var reg 32 # clk_counter [31:0] $end
$var reg 1 $ gen0_rtl_var $end
$var reg 1 % gen1_rtl_var $end
$var reg 1 & gen4_cyclix_genvar $end
$var reg 1 ' gen5_cyclix_genvar $end
$var reg 33 ( gen6_cyclix_genvar [32:0] $end
$var reg 1 ) gen7_cyclix_genvar $end
$var reg 32 * gensticky_clk_counter [31:0] $end
$var reg 32 + gensticky_input_spike [31:0] $end
$var reg 32 , gensticky_next_clk_count [31:0] $end
$var reg 32 - gensticky_tick [31:0] $end
$var reg 32 . gensticky_tick_period [31:0] $end
$var reg 32 / input_spike [31:0] $end
$var reg 32 0 next_clk_count [31:0] $end
$var reg 32 1 tick [31:0] $end
$var reg 32 2 tick_period [31:0] $end
$upscope $end
$upscope $end
$scope module Neuromorphic_design_tb $end
$scope module uut $end
$upscope $end
$upscope $end
$enddefinitions $end
#0
$dumpvars
b111110100 2
bx 1
bx 0
b1 /
bx .
bx -
bx ,
bx +
bx *
x)
b0 (
x'
x&
x%
x$
bx #
1"
0!
$end
#5000
0%
0)
b1 (
1$
1'
1&
b1 /
b111110100 2
b1 #
b1 0
b0 1
b0 -
b110010 .
b0 *
b0 ,
b0 +
1!
#10000
0!
#15000
1!
#20000
0!
0"
#25000
0)
b10 #
b10 0
b10 (
b111110100 .
b1 *
b1 ,
b1 +
1!
#30000
0!
#35000
0)
b11 #
b11 0
b11 (
b10 ,
b10 *
1!
#40000
0!
#45000
0)
b100 #
b100 0
b100 (
b11 *
b11 ,
1!
#50000
0!
#55000
0)
b101 #
b101 0
b101 (
b100 ,
b100 *
1!
#60000
0!
#65000
0)
b110 #
b110 0
b110 (
b101 *
b101 ,
1!
#70000
0!
#75000
0)
b111 #
b111 0
b111 (
b110 ,
b110 *
1!
#80000
0!
#85000
0)
b1000 #
b1000 0
b1000 (
b111 *
b111 ,
1!
#90000
0!
#95000
0)
b1001 #
b1001 0
b1001 (
b1000 ,
b1000 *
1!
#100000
0!
#105000
0)
b1010 #
b1010 0
b1010 (
b1001 *
b1001 ,
1!
#110000
0!
#115000
0)
b1011 #
b1011 0
b1011 (
b1010 ,
b1010 *
1!
#120000
0!
1"
#125000
0)
b1 /
b111110100 2
b1 #
b1 0
b1 (
b110010 .
b0 *
b0 ,
b0 +
1!
#130000
0!
#135000
1!
#140000
0!
0"
#145000
0)
b10 #
b10 0
b10 (
b111110100 .
b1 *
b1 ,
b1 +
1!
#150000
0!
#155000
0)
b11 #
b11 0
b11 (
b10 ,
b10 *
1!
#160000
0!
#165000
0)
b100 #
b100 0
b100 (
b11 *
b11 ,
1!
#170000
0!
#175000
0)
b101 #
b101 0
b101 (
b100 ,
b100 *
1!
#180000
0!
#185000
0)
b110 #
b110 0
b110 (
b101 *
b101 ,
1!
#190000
0!
#195000
0)
b111 #
b111 0
b111 (
b110 ,
b110 *
1!
#200000
0!
#205000
0)
b1000 #
b1000 0
b1000 (
b111 *
b111 ,
1!
#210000
0!
#215000
0)
b1001 #
b1001 0
b1001 (
b1000 ,
b1000 *
1!
#220000
0!
#225000
0)
b1010 #
b1010 0
b1010 (
b1001 *
b1001 ,
1!
#230000
0!
#235000
0)
b1011 #
b1011 0
b1011 (
b1010 ,
b1010 *
1!
#240000
0!
#245000
0)
b1100 #
b1100 0
b1100 (
b1011 *
b1011 ,
1!
#250000
0!
#255000
0)
b1101 #
b1101 0
b1101 (
b1100 ,
b1100 *
1!
#260000
0!
#265000
0)
b1110 #
b1110 0
b1110 (
b1101 *
b1101 ,
1!
#270000
0!
#275000
0)
b1111 #
b1111 0
b1111 (
b1110 ,
b1110 *
1!
#280000
0!
#285000
0)
b10000 #
b10000 0
b10000 (
b1111 *
b1111 ,
1!
#290000
0!
#295000
0)
b10001 #
b10001 0
b10001 (
b10000 ,
b10000 *
1!
#300000
0!
#305000
0)
b10010 #
b10010 0
b10010 (
b10001 *
b10001 ,
1!
#310000
0!
#315000
0)
b10011 #
b10011 0
b10011 (
b10010 ,
b10010 *
1!
#320000
0!
#325000
0)
b10100 #
b10100 0
b10100 (
b10011 *
b10011 ,
1!
#330000
0!
#335000
0)
b10101 #
b10101 0
b10101 (
b10100 ,
b10100 *
1!
#340000
0!
#345000
0)
b10110 #
b10110 0
b10110 (
b10101 *
b10101 ,
1!
#350000
0!
#355000
0)
b10111 #
b10111 0
b10111 (
b10110 ,
b10110 *
1!
#360000
0!
#365000
0)
b11000 #
b11000 0
b11000 (
b10111 *
b10111 ,
1!
#370000
0!
#375000
0)
b11001 #
b11001 0
b11001 (
b11000 ,
b11000 *
1!
#380000
0!
#385000
0)
b11010 #
b11010 0
b11010 (
b11001 *
b11001 ,
1!
#390000
0!
#395000
0)
b11011 #
b11011 0
b11011 (
b11010 ,
b11010 *
1!
#400000
0!
#405000
0)
b11100 #
b11100 0
b11100 (
b11011 *
b11011 ,
1!
#410000
0!
#415000
0)
b11101 #
b11101 0
b11101 (
b11100 ,
b11100 *
1!
#420000
0!
#425000
0)
b11110 #
b11110 0
b11110 (
b11101 *
b11101 ,
1!
#430000
0!
#435000
0)
b11111 #
b11111 0
b11111 (
b11110 ,
b11110 *
1!
#440000
0!
#445000
0)
b100000 #
b100000 0
b100000 (
b11111 *
b11111 ,
1!
#450000
0!
#455000
0)
b100001 #
b100001 0
b100001 (
b100000 ,
b100000 *
1!
#460000
0!
#465000
0)
b100010 #
b100010 0
b100010 (
b100001 *
b100001 ,
1!
#470000
0!
#475000
0)
b100011 #
b100011 0
b100011 (
b100010 ,
b100010 *
1!
#480000
0!
#485000
0)
b100100 #
b100100 0
b100100 (
b100011 *
b100011 ,
1!
#490000
0!
#495000
0)
b100101 #
b100101 0
b100101 (
b100100 ,
b100100 *
1!
#500000
0!
#505000
0)
b100110 #
b100110 0
b100110 (
b100101 *
b100101 ,
1!
#510000
0!
#515000
0)
b100111 #
b100111 0
b100111 (
b100110 ,
b100110 *
1!
#520000
0!
#525000
0)
b101000 #
b101000 0
b101000 (
b100111 *
b100111 ,
1!
#530000
0!
#535000
0)
b101001 #
b101001 0
b101001 (
b101000 ,
b101000 *
1!
#540000
0!
#545000
0)
b101010 #
b101010 0
b101010 (
b101001 *
b101001 ,
1!
#550000
0!
#555000
0)
b101011 #
b101011 0
b101011 (
b101010 ,
b101010 *
1!
#560000
0!
#565000
0)
b101100 #
b101100 0
b101100 (
b101011 *
b101011 ,
1!
#570000
0!
#575000
0)
b101101 #
b101101 0
b101101 (
b101100 ,
b101100 *
1!
#580000
0!
#585000
0)
b101110 #
b101110 0
b101110 (
b101101 *
b101101 ,
1!
#590000
0!
#595000
0)
b101111 #
b101111 0
b101111 (
b101110 ,
b101110 *
1!
#600000
0!
#605000
0)
b110000 #
b110000 0
b110000 (
b101111 *
b101111 ,
1!
#610000
0!
#615000
0)
b110001 #
b110001 0
b110001 (
b110000 ,
b110000 *
1!
#620000
0!
#625000
0)
b110010 #
b110010 0
b110010 (
b110001 *
b110001 ,
1!
#630000
0!
#635000
0)
b110011 #
b110011 0
b110011 (
b110010 ,
b110010 *
1!
#640000
0!
#645000
0)
b110100 #
b110100 0
b110100 (
b110011 *
b110011 ,
1!
#650000
0!
#655000
0)
b110101 #
b110101 0
b110101 (
b110100 ,
b110100 *
1!
#660000
0!
#665000
0)
b110110 #
b110110 0
b110110 (
b110101 *
b110101 ,
1!
#670000
0!
#675000
0)
b110111 #
b110111 0
b110111 (
b110110 ,
b110110 *
1!
#680000
0!
#685000
0)
b111000 #
b111000 0
b111000 (
b110111 *
b110111 ,
1!
#690000
0!
#695000
0)
b111001 #
b111001 0
b111001 (
b111000 ,
b111000 *
1!
#700000
0!
#705000
0)
b111010 #
b111010 0
b111010 (
b111001 *
b111001 ,
1!
#710000
0!
#715000
0)
b111011 #
b111011 0
b111011 (
b111010 ,
b111010 *
1!
#720000
0!
#725000
0)
b111100 #
b111100 0
b111100 (
b111011 *
b111011 ,
1!
#730000
0!
#735000
0)
b111101 #
b111101 0
b111101 (
b111100 ,
b111100 *
1!
#740000
0!
#745000
0)
b111110 #
b111110 0
b111110 (
b111101 *
b111101 ,
1!
#750000
0!
#755000
0)
b111111 #
b111111 0
b111111 (
b111110 ,
b111110 *
1!
#760000
0!
#765000
0)
b1000000 #
b1000000 0
b1000000 (
b111111 *
b111111 ,
1!
#770000
0!
#775000
0)
b1000001 #
b1000001 0
b1000001 (
b1000000 ,
b1000000 *
1!
#780000
0!
#785000
0)
b1000010 #
b1000010 0
b1000010 (
b1000001 *
b1000001 ,
1!
#790000
0!
#795000
0)
b1000011 #
b1000011 0
b1000011 (
b1000010 ,
b1000010 *
1!
#800000
0!
#805000
0)
b1000100 #
b1000100 0
b1000100 (
b1000011 *
b1000011 ,
1!
#810000
0!
#815000
0)
b1000101 #
b1000101 0
b1000101 (
b1000100 ,
b1000100 *
1!
#820000
0!
#825000
0)
b1000110 #
b1000110 0
b1000110 (
b1000101 *
b1000101 ,
1!
#830000
0!
#835000
0)
b1000111 #
b1000111 0
b1000111 (
b1000110 ,
b1000110 *
1!
#840000
0!
#845000
0)
b1001000 #
b1001000 0
b1001000 (
b1000111 *
b1000111 ,
1!
#850000
0!
#855000
0)
b1001001 #
b1001001 0
b1001001 (
b1001000 ,
b1001000 *
1!
#860000
0!
#865000
0)
b1001010 #
b1001010 0
b1001010 (
b1001001 *
b1001001 ,
1!
#870000
0!
#875000
0)
b1001011 #
b1001011 0
b1001011 (
b1001010 ,
b1001010 *
1!
#880000
0!
#885000
0)
b1001100 #
b1001100 0
b1001100 (
b1001011 *
b1001011 ,
1!
#890000
0!
#895000
0)
b1001101 #
b1001101 0
b1001101 (
b1001100 ,
b1001100 *
1!
#900000
0!
#905000
0)
b1001110 #
b1001110 0
b1001110 (
b1001101 *
b1001101 ,
1!
#910000
0!
#915000
0)
b1001111 #
b1001111 0
b1001111 (
b1001110 ,
b1001110 *
1!
#920000
0!
#925000
0)
b1010000 #
b1010000 0
b1010000 (
b1001111 *
b1001111 ,
1!
#930000
0!
#935000
0)
b1010001 #
b1010001 0
b1010001 (
b1010000 ,
b1010000 *
1!
#940000
0!
#945000
0)
b1010010 #
b1010010 0
b1010010 (
b1010001 *
b1010001 ,
1!
#950000
0!
#955000
0)
b1010011 #
b1010011 0
b1010011 (
b1010010 ,
b1010010 *
1!
#960000
0!
#965000
0)
b1010100 #
b1010100 0
b1010100 (
b1010011 *
b1010011 ,
1!
#970000
0!
#975000
0)
b1010101 #
b1010101 0
b1010101 (
b1010100 ,
b1010100 *
1!
#980000
0!
#985000
0)
b1010110 #
b1010110 0
b1010110 (
b1010101 *
b1010101 ,
1!
#990000
0!
#995000
0)
b1010111 #
b1010111 0
b1010111 (
b1010110 ,
b1010110 *
1!
#1000000
0!
#1005000
0)
b1011000 #
b1011000 0
b1011000 (
b1010111 *
b1010111 ,
1!
#1010000
0!
#1015000
0)
b1011001 #
b1011001 0
b1011001 (
b1011000 ,
b1011000 *
1!
#1020000
0!
#1025000
0)
b1011010 #
b1011010 0
b1011010 (
b1011001 *
b1011001 ,
1!
#1030000
0!
#1035000
0)
b1011011 #
b1011011 0
b1011011 (
b1011010 ,
b1011010 *
1!
#1040000
0!
#1045000
0)
b1011100 #
b1011100 0
b1011100 (
b1011011 *
b1011011 ,
1!
#1050000
0!
#1055000
0)
b1011101 #
b1011101 0
b1011101 (
b1011100 ,
b1011100 *
1!
#1060000
0!
#1065000
0)
b1011110 #
b1011110 0
b1011110 (
b1011101 *
b1011101 ,
1!
#1070000
0!
#1075000
0)
b1011111 #
b1011111 0
b1011111 (
b1011110 ,
b1011110 *
1!
#1080000
0!
#1085000
0)
b1100000 #
b1100000 0
b1100000 (
b1011111 *
b1011111 ,
1!
#1090000
0!
#1095000
0)
b1100001 #
b1100001 0
b1100001 (
b1100000 ,
b1100000 *
1!
#1100000
0!
#1105000
0)
b1100010 #
b1100010 0
b1100010 (
b1100001 *
b1100001 ,
1!
#1110000
0!
#1115000
0)
b1100011 #
b1100011 0
b1100011 (
b1100010 ,
b1100010 *
1!
#1120000
0!
#1125000
0)
b1100100 #
b1100100 0
b1100100 (
b1100011 *
b1100011 ,
1!
#1130000
0!
#1135000
0)
b1100101 #
b1100101 0
b1100101 (
b1100100 ,
b1100100 *
1!
#1140000
0!
#1145000
0)
b1100110 #
b1100110 0
b1100110 (
b1100101 *
b1100101 ,
1!
#1150000
0!
#1155000
0)
b1100111 #
b1100111 0
b1100111 (
b1100110 ,
b1100110 *
1!
#1160000
0!
#1165000
0)
b1101000 #
b1101000 0
b1101000 (
b1100111 *
b1100111 ,
1!
#1170000
0!
#1175000
0)
b1101001 #
b1101001 0
b1101001 (
b1101000 ,
b1101000 *
1!
#1180000
0!
#1185000
0)
b1101010 #
b1101010 0
b1101010 (
b1101001 *
b1101001 ,
1!
#1190000
0!
#1195000
0)
b1101011 #
b1101011 0
b1101011 (
b1101010 ,
b1101010 *
1!
#1200000
0!
#1205000
0)
b1101100 #
b1101100 0
b1101100 (
b1101011 *
b1101011 ,
1!
#1210000
0!
#1215000
0)
b1101101 #
b1101101 0
b1101101 (
b1101100 ,
b1101100 *
1!
#1220000
0!
#1225000
0)
b1101110 #
b1101110 0
b1101110 (
b1101101 *
b1101101 ,
1!
#1230000
0!
#1235000
0)
b1101111 #
b1101111 0
b1101111 (
b1101110 ,
b1101110 *
1!
#1240000
0!
#1245000
0)
b1110000 #
b1110000 0
b1110000 (
b1101111 *
b1101111 ,
1!
#1250000
0!
#1255000
0)
b1110001 #
b1110001 0
b1110001 (
b1110000 ,
b1110000 *
1!
#1260000
0!
#1265000
0)
b1110010 #
b1110010 0
b1110010 (
b1110001 *
b1110001 ,
1!
#1270000
0!
#1275000
0)
b1110011 #
b1110011 0
b1110011 (
b1110010 ,
b1110010 *
1!
#1280000
0!
#1285000
0)
b1110100 #
b1110100 0
b1110100 (
b1110011 *
b1110011 ,
1!
#1290000
0!
#1295000
0)
b1110101 #
b1110101 0
b1110101 (
b1110100 ,
b1110100 *
1!
#1300000
0!
#1305000
0)
b1110110 #
b1110110 0
b1110110 (
b1110101 *
b1110101 ,
1!
#1310000
0!
#1315000
0)
b1110111 #
b1110111 0
b1110111 (
b1110110 ,
b1110110 *
1!
#1320000
0!
#1325000
0)
b1111000 #
b1111000 0
b1111000 (
b1110111 *
b1110111 ,
1!
#1330000
0!
#1335000
0)
b1111001 #
b1111001 0
b1111001 (
b1111000 ,
b1111000 *
1!
#1340000
0!
#1345000
0)
b1111010 #
b1111010 0
b1111010 (
b1111001 *
b1111001 ,
1!
#1350000
0!
#1355000
0)
b1111011 #
b1111011 0
b1111011 (
b1111010 ,
b1111010 *
1!
#1360000
0!
#1365000
0)
b1111100 #
b1111100 0
b1111100 (
b1111011 *
b1111011 ,
1!
#1370000
0!
#1375000
0)
b1111101 #
b1111101 0
b1111101 (
b1111100 ,
b1111100 *
1!
#1380000
0!
#1385000
0)
b1111110 #
b1111110 0
b1111110 (
b1111101 *
b1111101 ,
1!
#1390000
0!
#1395000
0)
b1111111 #
b1111111 0
b1111111 (
b1111110 ,
b1111110 *
1!
#1400000
0!
#1405000
0)
b10000000 #
b10000000 0
b10000000 (
b1111111 *
b1111111 ,
1!
#1410000
0!
#1415000
0)
b10000001 #
b10000001 0
b10000001 (
b10000000 ,
b10000000 *
1!
#1420000
0!
#1425000
0)
b10000010 #
b10000010 0
b10000010 (
b10000001 *
b10000001 ,
1!
#1430000
0!
#1435000
0)
b10000011 #
b10000011 0
b10000011 (
b10000010 ,
b10000010 *
1!
#1440000
0!
#1445000
0)
b10000100 #
b10000100 0
b10000100 (
b10000011 *
b10000011 ,
1!
#1450000
0!
#1455000
0)
b10000101 #
b10000101 0
b10000101 (
b10000100 ,
b10000100 *
1!
#1460000
0!
#1465000
0)
b10000110 #
b10000110 0
b10000110 (
b10000101 *
b10000101 ,
1!
#1470000
0!
#1475000
0)
b10000111 #
b10000111 0
b10000111 (
b10000110 ,
b10000110 *
1!
#1480000
0!
#1485000
0)
b10001000 #
b10001000 0
b10001000 (
b10000111 *
b10000111 ,
1!
#1490000
0!
#1495000
0)
b10001001 #
b10001001 0
b10001001 (
b10001000 ,
b10001000 *
1!
#1500000
0!
#1505000
0)
b10001010 #
b10001010 0
b10001010 (
b10001001 *
b10001001 ,
1!
#1510000
0!
#1515000
0)
b10001011 #
b10001011 0
b10001011 (
b10001010 ,
b10001010 *
1!
#1520000
0!
#1525000
0)
b10001100 #
b10001100 0
b10001100 (
b10001011 *
b10001011 ,
1!
#1530000
0!
#1535000
0)
b10001101 #
b10001101 0
b10001101 (
b10001100 ,
b10001100 *
1!
#1540000
0!
#1545000
0)
b10001110 #
b10001110 0
b10001110 (
b10001101 *
b10001101 ,
1!
#1550000
0!
#1555000
0)
b10001111 #
b10001111 0
b10001111 (
b10001110 ,
b10001110 *
1!
#1560000
0!
#1565000
0)
b10010000 #
b10010000 0
b10010000 (
b10001111 *
b10001111 ,
1!
#1570000
0!
#1575000
0)
b10010001 #
b10010001 0
b10010001 (
b10010000 ,
b10010000 *
1!
#1580000
0!
#1585000
0)
b10010010 #
b10010010 0
b10010010 (
b10010001 *
b10010001 ,
1!
#1590000
0!
#1595000
0)
b10010011 #
b10010011 0
b10010011 (
b10010010 ,
b10010010 *
1!
#1600000
0!
#1605000
0)
b10010100 #
b10010100 0
b10010100 (
b10010011 *
b10010011 ,
1!
#1610000
0!
#1615000
0)
b10010101 #
b10010101 0
b10010101 (
b10010100 ,
b10010100 *
1!
#1620000
0!
#1625000
0)
b10010110 #
b10010110 0
b10010110 (
b10010101 *
b10010101 ,
1!
#1630000
0!
#1635000
0)
b10010111 #
b10010111 0
b10010111 (
b10010110 ,
b10010110 *
1!
#1640000
0!
#1645000
0)
b10011000 #
b10011000 0
b10011000 (
b10010111 *
b10010111 ,
1!
#1650000
0!
#1655000
0)
b10011001 #
b10011001 0
b10011001 (
b10011000 ,
b10011000 *
1!
#1660000
0!
#1665000
0)
b10011010 #
b10011010 0
b10011010 (
b10011001 *
b10011001 ,
1!
#1670000
0!
#1675000
0)
b10011011 #
b10011011 0
b10011011 (
b10011010 ,
b10011010 *
1!
#1680000
0!
#1685000
0)
b10011100 #
b10011100 0
b10011100 (
b10011011 *
b10011011 ,
1!
#1690000
0!
#1695000
0)
b10011101 #
b10011101 0
b10011101 (
b10011100 ,
b10011100 *
1!
#1700000
0!
#1705000
0)
b10011110 #
b10011110 0
b10011110 (
b10011101 *
b10011101 ,
1!
#1710000
0!
#1715000
0)
b10011111 #
b10011111 0
b10011111 (
b10011110 ,
b10011110 *
1!
#1720000
0!
#1725000
0)
b10100000 #
b10100000 0
b10100000 (
b10011111 *
b10011111 ,
1!
#1730000
0!
#1735000
0)
b10100001 #
b10100001 0
b10100001 (
b10100000 ,
b10100000 *
1!
#1740000
0!
#1745000
0)
b10100010 #
b10100010 0
b10100010 (
b10100001 *
b10100001 ,
1!
#1750000
0!
#1755000
0)
b10100011 #
b10100011 0
b10100011 (
b10100010 ,
b10100010 *
1!
#1760000
0!
#1765000
0)
b10100100 #
b10100100 0
b10100100 (
b10100011 *
b10100011 ,
1!
#1770000
0!
#1775000
0)
b10100101 #
b10100101 0
b10100101 (
b10100100 ,
b10100100 *
1!
#1780000
0!
#1785000
0)
b10100110 #
b10100110 0
b10100110 (
b10100101 *
b10100101 ,
1!
#1790000
0!
#1795000
0)
b10100111 #
b10100111 0
b10100111 (
b10100110 ,
b10100110 *
1!
#1800000
0!
#1805000
0)
b10101000 #
b10101000 0
b10101000 (
b10100111 *
b10100111 ,
1!
#1810000
0!
#1815000
0)
b10101001 #
b10101001 0
b10101001 (
b10101000 ,
b10101000 *
1!
#1820000
0!
#1825000
0)
b10101010 #
b10101010 0
b10101010 (
b10101001 *
b10101001 ,
1!
#1830000
0!
#1835000
0)
b10101011 #
b10101011 0
b10101011 (
b10101010 ,
b10101010 *
1!
#1840000
0!
#1845000
0)
b10101100 #
b10101100 0
b10101100 (
b10101011 *
b10101011 ,
1!
#1850000
0!
#1855000
0)
b10101101 #
b10101101 0
b10101101 (
b10101100 ,
b10101100 *
1!
#1860000
0!
#1865000
0)
b10101110 #
b10101110 0
b10101110 (
b10101101 *
b10101101 ,
1!
#1870000
0!
#1875000
0)
b10101111 #
b10101111 0
b10101111 (
b10101110 ,
b10101110 *
1!
#1880000
0!
#1885000
0)
b10110000 #
b10110000 0
b10110000 (
b10101111 *
b10101111 ,
1!
#1890000
0!
#1895000
0)
b10110001 #
b10110001 0
b10110001 (
b10110000 ,
b10110000 *
1!
#1900000
0!
#1905000
0)
b10110010 #
b10110010 0
b10110010 (
b10110001 *
b10110001 ,
1!
#1910000
0!
#1915000
0)
b10110011 #
b10110011 0
b10110011 (
b10110010 ,
b10110010 *
1!
#1920000
0!
#1925000
0)
b10110100 #
b10110100 0
b10110100 (
b10110011 *
b10110011 ,
1!
#1930000
0!
#1935000
0)
b10110101 #
b10110101 0
b10110101 (
b10110100 ,
b10110100 *
1!
#1940000
0!
#1945000
0)
b10110110 #
b10110110 0
b10110110 (
b10110101 *
b10110101 ,
1!
#1950000
0!
#1955000
0)
b10110111 #
b10110111 0
b10110111 (
b10110110 ,
b10110110 *
1!
#1960000
0!
#1965000
0)
b10111000 #
b10111000 0
b10111000 (
b10110111 *
b10110111 ,
1!
#1970000
0!
#1975000
0)
b10111001 #
b10111001 0
b10111001 (
b10111000 ,
b10111000 *
1!
#1980000
0!
#1985000
0)
b10111010 #
b10111010 0
b10111010 (
b10111001 *
b10111001 ,
1!
#1990000
0!
#1995000
0)
b10111011 #
b10111011 0
b10111011 (
b10111010 ,
b10111010 *
1!
#2000000
0!
#2005000
0)
b10111100 #
b10111100 0
b10111100 (
b10111011 *
b10111011 ,
1!
#2010000
0!
#2015000
0)
b10111101 #
b10111101 0
b10111101 (
b10111100 ,
b10111100 *
1!
#2020000
0!
#2025000
0)
b10111110 #
b10111110 0
b10111110 (
b10111101 *
b10111101 ,
1!
#2030000
0!
#2035000
0)
b10111111 #
b10111111 0
b10111111 (
b10111110 ,
b10111110 *
1!
#2040000
0!
#2045000
0)
b11000000 #
b11000000 0
b11000000 (
b10111111 *
b10111111 ,
1!
#2050000
0!
#2055000
0)
b11000001 #
b11000001 0
b11000001 (
b11000000 ,
b11000000 *
1!
#2060000
0!
#2065000
0)
b11000010 #
b11000010 0
b11000010 (
b11000001 *
b11000001 ,
1!
#2070000
0!
#2075000
0)
b11000011 #
b11000011 0
b11000011 (
b11000010 ,
b11000010 *
1!
#2080000
0!
#2085000
0)
b11000100 #
b11000100 0
b11000100 (
b11000011 *
b11000011 ,
1!
#2090000
0!
#2095000
0)
b11000101 #
b11000101 0
b11000101 (
b11000100 ,
b11000100 *
1!
#2100000
0!
#2105000
0)
b11000110 #
b11000110 0
b11000110 (
b11000101 *
b11000101 ,
1!
#2110000
0!
#2115000
0)
b11000111 #
b11000111 0
b11000111 (
b11000110 ,
b11000110 *
1!
#2120000
0!
#2125000
0)
b11001000 #
b11001000 0
b11001000 (
b11000111 *
b11000111 ,
1!
#2130000
0!
#2135000
0)
b11001001 #
b11001001 0
b11001001 (
b11001000 ,
b11001000 *
1!
#2140000
0!
#2145000
0)
b11001010 #
b11001010 0
b11001010 (
b11001001 *
b11001001 ,
1!
#2150000
0!
#2155000
0)
b11001011 #
b11001011 0
b11001011 (
b11001010 ,
b11001010 *
1!
#2160000
0!
#2165000
0)
b11001100 #
b11001100 0
b11001100 (
b11001011 *
b11001011 ,
1!
#2170000
0!
#2175000
0)
b11001101 #
b11001101 0
b11001101 (
b11001100 ,
b11001100 *
1!
#2180000
0!
#2185000
0)
b11001110 #
b11001110 0
b11001110 (
b11001101 *
b11001101 ,
1!
#2190000
0!
#2195000
0)
b11001111 #
b11001111 0
b11001111 (
b11001110 ,
b11001110 *
1!
#2200000
0!
#2205000
0)
b11010000 #
b11010000 0
b11010000 (
b11001111 *
b11001111 ,
1!
#2210000
0!
#2215000
0)
b11010001 #
b11010001 0
b11010001 (
b11010000 ,
b11010000 *
1!
#2220000
0!
#2225000
0)
b11010010 #
b11010010 0
b11010010 (
b11010001 *
b11010001 ,
1!
#2230000
0!
#2235000
0)
b11010011 #
b11010011 0
b11010011 (
b11010010 ,
b11010010 *
1!
#2240000
0!
#2245000
0)
b11010100 #
b11010100 0
b11010100 (
b11010011 *
b11010011 ,
1!
#2250000
0!
#2255000
0)
b11010101 #
b11010101 0
b11010101 (
b11010100 ,
b11010100 *
1!
#2260000
0!
#2265000
0)
b11010110 #
b11010110 0
b11010110 (
b11010101 *
b11010101 ,
1!
#2270000
0!
#2275000
0)
b11010111 #
b11010111 0
b11010111 (
b11010110 ,
b11010110 *
1!
