designs/rtl/lif_acc/LIF_acceleralor_256_256_4/sverilog/Neuromorphic_design.svh
// ===========================================================
// RTL generated by ActiveCore framework
// Date: 2024-09-28 15:42:31
// Copyright Alexander Antonov <antonov.alex.alex@gmail.com>
// ===========================================================

`ifndef __Neuromorphic_design_h_
`define __Neuromorphic_design_h_

`endif // __Neuromorphic_design_h_

designs/rtl/lif_acc/LIF_acceleralor_256_256_4/sverilog/Neuromorphic_design.sv
// ===========================================================
// RTL generated by ActiveCore framework
// Date: 2024-09-28 15:42:31
// Copyright Alexander Antonov <antonov.alex.alex@gmail.com>
// ===========================================================

`include "Neuromorphic_design.svh"

module Neuromorphic_design (
	input logic unsigned [0:0] clk_i
	, input logic unsigned [0:0] rst_i
);


logic unsigned [31:0] tick;
logic unsigned [31:0] tick_period;
logic unsigned [31:0] clk_counter;
logic unsigned [31:0] next_clk_count;
logic unsigned [31:0] input_spike;
logic unsigned [0:0] gen4_cyclix_genvar;
logic unsigned [0:0] gen5_cyclix_genvar;
logic unsigned [32:0] gen6_cyclix_genvar;
logic unsigned [0:0] gen7_cyclix_genvar;
logic unsigned [0:0] gen0_rtl_var;
logic unsigned [0:0] gen1_rtl_var;

logic unsigned [31:0] gensticky_tick;
always_ff @(posedge clk_i)
	if (rst_i)
		begin
		gensticky_tick <= 32'd0;
		end
	else
		begin
		gensticky_tick <= tick;
		end

logic unsigned [31:0] gensticky_tick_period;
always_ff @(posedge clk_i)
	if (rst_i)
		begin
		gensticky_tick_period <= 32'd5;
		end
	else
		begin
		gensticky_tick_period <= tick_period;
		end

logic unsigned [31:0] gensticky_clk_counter;
always_ff @(posedge clk_i)
	if (rst_i)
		begin
		gensticky_clk_counter <= 32'd0;
		end
	else
		begin
		gensticky_clk_counter <= clk_counter;
		end

logic unsigned [31:0] gensticky_next_clk_count;
always_ff @(posedge clk_i)
	if (rst_i)
		begin
		gensticky_next_clk_count <= 32'd0;
		end
	else
		begin
		gensticky_next_clk_count <= next_clk_count;
		end

logic unsigned [31:0] gensticky_input_spike;
always_ff @(posedge clk_i)
	if (rst_i)
		begin
		gensticky_input_spike <= 32'd0;
		end
	else
		begin
		gensticky_input_spike <= input_spike;
		end


always_comb
	begin
	tick = 32'd0;
	gen6_cyclix_genvar = 32'd0;
	next_clk_count = 32'd0;
	clk_counter = 32'd0;
	tick_period = gensticky_tick_period;
	tick = gensticky_tick;
	next_clk_count = gensticky_next_clk_count;
	clk_counter = gensticky_clk_counter;
	input_spike = gensticky_input_spike;
	// Buffering globals
	// Processing dlychains
	// fifo_in buffering
	// subproc fifo_in buffering
	// Payload logic
	tick_period = 32'd5;
	gen4_cyclix_genvar = (tick_period != clk_counter);
	gen5_cyclix_genvar = gen4_cyclix_genvar;
	gen0_rtl_var = gen5_cyclix_genvar;
	if (gen0_rtl_var)
		begin
		tick = 32'd0;
		gen6_cyclix_genvar = (clk_counter + 32'd1);
		next_clk_count = gen6_cyclix_genvar;
		clk_counter = next_clk_count;
		end
	gen7_cyclix_genvar = 1'd0;
	gen7_cyclix_genvar = (gen7_cyclix_genvar || gen5_cyclix_genvar);
	gen7_cyclix_genvar = !gen7_cyclix_genvar;
	gen1_rtl_var = gen7_cyclix_genvar;
	if (gen1_rtl_var)
		begin
		tick = 32'd1;
		clk_counter = 32'd0;
		end
	input_spike = 32'd1;
	end


endmodule

designs/rtl/lif_acc/LIF_acceleralor_256_256_4/sverilog/tb_tick.sv
`timescale 1ns/1ps

module Neuromorphic_design_tb;

  // Порты для подключения к тестируемому модулю
  logic unsigned [0:0] clk_i;
  logic unsigned [0:0] rst_i;

  // Параметры для симуляции
  parameter CLK_PERIOD = 10; // Период тактового сигнала 10 нс

  // Экземпляр тестируемого модуля
  Neuromorphic_design uut (
    .clk_i(clk_i),
    .rst_i(rst_i)
  );

  // Генерация тактового сигнала
  always #(CLK_PERIOD / 2) clk_i = ~clk_i;

  // Процесс инициализации и тестирования
  initial begin
    // Инициализация сигналов
    clk_i = 0;
    rst_i = 1;

    // Открываем файл для VCD
    $dumpfile("Neuromorphic_design_tb.vcd");
    $dumpvars(0, Neuromorphic_design_tb);
    $dumpvars(0, uut);



    // Старт тестирования
    #20; // Задержка для начальной стабилизации

    // Сброс системы
    rst_i = 0;
    #100;
    
    // Поднимаем сигнал сброса для перезапуска
    rst_i = 1;
    #20;
    rst_i = 0;

    // Наблюдаем за сигналами некоторое время
    #50000;

    // Завершение симуляции
    $finish;
  end

  // Отслеживание сигналов в консоли
  always @(posedge clk_i) begin
    // $display("Time: %0t | tick: %0d, tick_period: %0d, clk_counter: %0d, next_clk_count: %0d, input_spike: %0d",
    //          $time, tick, tick_period, clk_counter, next_clk_count, input_spike);
  end

endmodule

designs/rtl/lif_acc/LIF_acceleralor_256_256_4/sverilog/Neuromorphic_design_tb.vcd
$date
	Sat Sep 28 16:07:56 2024
$end
$version
	Icarus Verilog
$end
$timescale
	1ps
$end
$scope module Neuromorphic_design_tb $end
$var reg 1 ! clk_i $end
$var reg 1 " rst_i $end
$scope module uut $end
$var wire 1 ! clk_i $end
$var wire 1 " rst_i $end
$var reg 32 # clk_counter [31:0] $end
$var reg 1 $ gen0_rtl_var $end
$var reg 1 % gen1_rtl_var $end
$var reg 1 & gen4_cyclix_genvar $end
$var reg 1 ' gen5_cyclix_genvar $end
$var reg 33 ( gen6_cyclix_genvar [32:0] $end
$var reg 1 ) gen7_cyclix_genvar $end
$var reg 32 * gensticky_clk_counter [31:0] $end
$var reg 32 + gensticky_input_spike [31:0] $end
$var reg 32 , gensticky_next_clk_count [31:0] $end
$var reg 32 - gensticky_tick [31:0] $end
$var reg 32 . gensticky_tick_period [31:0] $end
$var reg 32 / input_spike [31:0] $end
$var reg 32 0 next_clk_count [31:0] $end
$var reg 32 1 tick [31:0] $end
$var reg 32 2 tick_period [31:0] $end
$upscope $end
$upscope $end
$scope module Neuromorphic_design_tb $end
$scope module uut $end
$upscope $end
$upscope $end
$enddefinitions $end
#0
$dumpvars
b101 2
bx 1
bx 0
b1 /
bx .
bx -
bx ,
bx +
bx *
x)
b0 (
x'
x&
x%
x$
bx #
1"
0!
$end
#5000
0%
0)
b1 (
1$
1'
1&
b1 /
b1 #
b1 0
b0 1
b0 -
b101 .
b0 *
b0 ,
b0 +
1!
#10000
0!
#15000
1!
#20000
0!
0"
#25000
0)
b10 #
b10 0
b10 (
b1 *
b1 ,
b1 +
1!
#30000
0!
#35000
0)
b11 #
b11 0
b11 (
b10 ,
b10 *
1!
#40000
0!
#45000
0)
b100 #
b100 0
b100 (
b11 *
b11 ,
1!
#50000
0!
#55000
0)
b101 #
b101 0
b101 (
b100 ,
b100 *
1!
#60000
0!
#65000
b1 1
1%
1)
0$
0'
0&
b0 #
b101 0
b0 (
b101 *
b101 ,
1!
#70000
0!
#75000
0%
0)
b1 #
b1 (
1$
1'
1&
b1 0
b0 1
b0 *
b1 -
1!
#80000
0!
#85000
0)
b10 #
b10 0
b10 (
b0 -
b1 *
b1 ,
1!
#90000
0!
#95000
0)
b11 #
b11 0
b11 (
b10 ,
b10 *
1!
#100000
0!
#105000
0)
b100 #
b100 0
b100 (
b11 *
b11 ,
1!
#110000
0!
#115000
0)
b101 #
b101 0
b101 (
b100 ,
b100 *
1!
#120000
0!
1"
#125000
0)
b1 /
b1 #
b1 0
b1 (
b0 *
b0 ,
b0 +
1!
#130000
0!
#135000
1!
#140000
0!
0"
#145000
0)
b10 #
b10 0
b10 (
b1 *
b1 ,
b1 +
1!
#150000
0!
#155000
0)
b11 #
b11 0
b11 (
b10 ,
b10 *
1!
#160000
0!
#165000
0)
b100 #
b100 0
b100 (
b11 *
b11 ,
1!
#170000
0!
#175000
0)
b101 #
b101 0
b101 (
b100 ,
b100 *
1!
#180000
0!
#185000
b1 1
1%
1)
0$
0'
0&
b0 #
b101 0
b0 (
b101 *
b101 ,
1!
#190000
0!
#195000
0%
0)
b1 #
b1 (
1$
1'
1&
b1 0
b0 1
b0 *
b1 -
1!
#200000
0!
#205000
0)
b10 #
b10 0
b10 (
b0 -
b1 *
b1 ,
1!
#210000
0!
#215000
0)
b11 #
b11 0
b11 (
b10 ,
b10 *
1!
#220000
0!
#225000
0)
b100 #
b100 0
b100 (
b11 *
b11 ,
1!
#230000
0!
#235000
0)
b101 #
b101 0
b101 (
b100 ,
b100 *
1!
#240000
0!
#245000
b1 1
1%
1)
0$
0'
0&
b0 #
b101 0
b0 (
b101 *
b101 ,
1!
#250000
0!
#255000
0%
0)
b1 #
b1 (
1$
1'
1&
b1 0
b0 1
b0 *
b1 -
1!
#260000
0!
#265000
0)
b10 #
b10 0
b10 (
b0 -
b1 *
b1 ,
1!
#270000
0!
#275000
0)
b11 #
b11 0
b11 (
b10 ,
b10 *
1!
#280000
0!
#285000
0)
b100 #
b100 0
b100 (
b11 *
b11 ,
1!
#290000
0!
#295000
0)
b101 #
b101 0
b101 (
b100 ,
b100 *
1!
#300000
0!
#305000
b1 1
1%
1)
0$
0'
0&
b0 #
b101 0
b0 (
b101 *
b101 ,
1!
#310000
0!
#315000
0%
0)
b1 #
b1 (
1$
1'
1&
b1 0
b0 1
b0 *
b1 -
1!
#320000
0!
#325000
0)
b10 #
b10 0
b10 (
b0 -
b1 *
b1 ,
1!
#330000
0!
#335000
0)
b11 #
b11 0
b11 (
b10 ,
b10 *
1!
#340000
0!
#345000
0)
b100 #
b100 0
b100 (
b11 *
b11 ,
1!
#350000
0!
#355000
0)
b101 #
b101 0
b101 (
b100 ,
b100 *
1!
#360000
0!
#365000
b1 1
1%
1)
0$
0'
0&
b0 #
b101 0
b0 (
b101 *
b101 ,
1!
#370000
0!
#375000
0%
0)
b1 #
b1 (
1$
1'
1&
b1 0
b0 1
b0 *
b1 -
1!
#380000
0!
#385000
0)
b10 #
b10 0
b10 (
b0 -
b1 *
b1 ,
1!
#390000
0!
#395000
0)
b11 #
b11 0
b11 (
b10 ,
b10 *
1!
#400000
0!
#405000
0)
b100 #
b100 0
b100 (
b11 *
b11 ,
1!
#410000
0!
#415000
0)
b101 #
b101 0
b101 (
b100 ,
b100 *
1!
#420000
0!
#425000
b1 1
1%
1)
0$
0'
0&
b0 #
b101 0
b0 (
b101 *
b101 ,
1!
#430000
0!
#435000
0%
0)
b1 #
b1 (
1$
1'
1&
b1 0
b0 1
b0 *
b1 -
1!
#440000
0!
#445000
0)
b10 #
b10 0
b10 (
b0 -
b1 *
b1 ,
1!
#450000
0!
#455000
0)
b11 #
b11 0
b11 (
b10 ,
b10 *
1!
#460000
0!
#465000
0)
b100 #
b100 0
b100 (
b11 *
b11 ,
1!
#470000
0!
#475000
0)
b101 #
b101 0
b101 (
b100 ,
b100 *
1!
#480000
0!
#485000
b1 1
1%
1)
0$
0'
0&
b0 #
b101 0
b0 (
b101 *
b101 ,
1!
#490000
0!
#495000
0%
0)
b1 #
b1 (
1$
1'
1&
b1 0
b0 1
b0 *
b1 -
1!
#500000
0!
#505000
0)
b10 #
b10 0
b10 (
b0 -
b1 *
b1 ,
1!
#510000
0!
#515000
0)
b11 #
b11 0
b11 (
b10 ,
b10 *
1!
#520000
0!
#525000
0)
b100 #
b100 0
b100 (
b11 *
b11 ,
1!
#530000
0!
#535000
0)
b101 #
b101 0
b101 (
b100 ,
b100 *
1!
#540000
0!
#545000
b1 1
1%
1)
0$
0'
0&
b0 #
b101 0
b0 (
b101 *
b101 ,
1!
#550000
0!
#555000
0%
0)
b1 #
b1 (
1$
1'
1&
b1 0
b0 1
b0 *
b1 -
1!
#560000
0!
#565000
0)
b10 #
b10 0
b10 (
b0 -
b1 *
b1 ,
1!
#570000
0!
#575000
0)
b11 #
b11 0
b11 (
b10 ,
b10 *
1!
#580000
0!
#585000
0)
b100 #
b100 0
b100 (
b11 *
b11 ,
1!
#590000
0!
#595000
0)
b101 #
b101 0
b101 (
b100 ,
b100 *
1!
#600000
0!
#605000
b1 1
1%
1)
0$
0'
0&
b0 #
b101 0
b0 (
b101 *
b101 ,
1!
#610000
0!
#615000
0%
0)
b1 #
b1 (
1$
1'
1&
b1 0
b0 1
b0 *
b1 -
1!
#620000
0!
#625000
0)
b10 #
b10 0
b10 (
b0 -
b1 *
b1 ,
1!
#630000
0!
#635000
0)
b11 #
b11 0
b11 (
b10 ,
b10 *
1!
#640000
0!
#645000
0)
b100 #
b100 0
b100 (
b11 *
b11 ,
1!
#650000
0!
#655000
0)
b101 #
b101 0
b101 (
b100 ,
b100 *
1!
#660000
0!
#665000
b1 1
1%
1)
0$
0'
0&
b0 #
b101 0
b0 (
b101 *
b101 ,
1!
#670000
0!
#675000
0%
0)
b1 #
b1 (
1$
1'
1&
b1 0
b0 1
b0 *
b1 -
1!
#680000
0!
#685000
0)
b10 #
b10 0
b10 (
b0 -
b1 *
b1 ,
1!
#690000
0!
#695000
0)
b11 #
b11 0
b11 (
b10 ,
b10 *
1!
#700000
0!
#705000
0)
b100 #
b100 0
b100 (
b11 *
b11 ,
1!
#710000
0!
#715000
0)
b101 #
b101 0
b101 (
b100 ,
b100 *
1!
#720000
0!
#725000
b1 1
1%
1)
0$
0'
0&
b0 #
b101 0
b0 (
b101 *
b101 ,
1!
#730000
0!
#735000
0%
0)
b1 #
b1 (
1$
1'
1&
b1 0
b0 1
b0 *
b1 -
1!
#740000
0!
#745000
0)
b10 #
b10 0
b10 (
b0 -
b1 *
b1 ,
1!
#750000
0!
#755000
0)
b11 #
b11 0
b11 (
b10 ,
b10 *
1!
#760000
0!
#765000
0)
b100 #
b100 0
b100 (
b11 *
b11 ,
1!
#770000
0!
#775000
0)
b101 #
b101 0
b101 (
b100 ,
b100 *
1!
#780000
0!
#785000
b1 1
1%
1)
0$
0'
0&
b0 #
b101 0
b0 (
b101 *
b101 ,
1!
#790000
0!
#795000
0%
0)
b1 #
b1 (
1$
1'
1&
b1 0
b0 1
b0 *
b1 -
1!
#800000
0!
#805000
0)
b10 #
b10 0
b10 (
b0 -
b1 *
b1 ,
1!
#810000
0!
#815000
0)
b11 #
b11 0
b11 (
b10 ,
b10 *
1!
#820000
0!
#825000
0)
b100 #
b100 0
b100 (
b11 *
b11 ,
1!
#830000
0!
#835000
0)
b101 #
b101 0
b101 (
b100 ,
b100 *
1!
#840000
0!
#845000
b1 1
1%
1)
0$
0'
0&
b0 #
b101 0
b0 (
b101 *
b101 ,
1!
#850000
0!
#855000
0%
0)
b1 #
b1 (
1$
1'
1&
b1 0
b0 1
b0 *
b1 -
1!
#860000
0!
#865000
0)
b10 #
b10 0
b10 (
b0 -
b1 *
b1 ,
1!
#870000
0!
#875000
0)
b11 #
b11 0
b11 (
b10 ,
b10 *
1!
#880000
0!
#885000
0)
b100 #
b100 0
b100 (
b11 *
b11 ,
1!
#890000
0!
#895000
0)
b101 #
b101 0
b101 (
b100 ,
b100 *
1!
#900000
0!
#905000
b1 1
1%
1)
0$
0'
0&
b0 #
b101 0
b0 (
b101 *
b101 ,
1!
#910000
0!
#915000
0%
0)
b1 #
b1 (
1$
1'
1&
b1 0
b0 1
b0 *
b1 -
1!
#920000
0!
#925000
0)
b10 #
b10 0
b10 (
b0 -
b1 *
b1 ,
1!
#930000
0!
#935000
0)
b11 #
b11 0
b11 (
b10 ,
b10 *
1!
#940000
0!
#945000
0)
b100 #
b100 0
b100 (
b11 *
b11 ,
1!
#950000
0!
#955000
0)
b101 #
b101 0
b101 (
b100 ,
b100 *
1!
#960000
0!
#965000
b1 1
1%
1)
0$
0'
0&
b0 #
b101 0
b0 (
b101 *
b101 ,
1!
#970000
0!
#975000
0%
0)
b1 #
b1 (
1$
1'
1&
b1 0
b0 1
b0 *
b1 -
1!
#980000
0!
#985000
0)
b10 #
b10 0
b10 (
b0 -
b1 *
b1 ,
1!
#990000
0!
#995000
0)
b11 #
b11 0
b11 (
b10 ,
b10 *
1!
#1000000
0!
#1005000
0)
b100 #
b100 0
b100 (
b11 *
b11 ,
1!
#1010000
0!
#1015000
0)
b101 #
b101 0
b101 (
b100 ,
b100 *
1!
#1020000
0!
#1025000
b1 1
1%
1)
0$
0'
0&
b0 #
b101 0
b0 (
b101 *
b101 ,
1!
#1030000
0!
#1035000
0%
0)
b1 #
b1 (
1$
1'
1&
b1 0
b0 1
b0 *
b1 -
1!
#1040000
0!
#1045000
0)
b10 #
b10 0
b10 (
b0 -
b1 *
b1 ,
1!
#1050000
0!
#1055000
0)
b11 #
b11 0
b11 (
b10 ,
b10 *
1!
#1060000
0!
#1065000
0)
b100 #
b100 0
b100 (
b11 *
b11 ,
1!
#1070000
0!
#1075000
0)
b101 #
b101 0
b101 (
b100 ,
b100 *
1!
#1080000
0!
#1085000
b1 1
1%
1)
0$
0'
0&
b0 #
b101 0
b0 (
b101 *
b101 ,
1!
#1090000
0!
#1095000
0%
0)
b1 #
b1 (
1$
1'
1&
b1 0
b0 1
b0 *
b1 -
1!
#1100000
0!
#1105000
0)
b10 #
b10 0
b10 (
b0 -
b1 *
b1 ,
1!
#1110000
0!
#1115000
0)
b11 #
b11 0
b11 (
b10 ,
b10 *
1!
#1120000
0!
#1125000
0)
b100 #
b100 0
b100 (
b11 *
b11 ,
1!
#1130000
0!
#1135000
0)
b101 #
b101 0
b101 (
b100 ,
b100 *
1!
#1140000
0!
#1145000
b1 1
1%
1)
0$
0'
0&
b0 #
b101 0
b0 (
b101 *
b101 ,
1!
#1150000
0!
#1155000
0%
0)
b1 #
b1 (
1$
1'
1&
b1 0
b0 1
b0 *
b1 -
1!
#1160000
0!
#1165000
0)
b10 #
b10 0
b10 (
b0 -
b1 *
b1 ,
1!
#1170000
0!
#1175000
0)
b11 #
b11 0
b11 (
b10 ,
b10 *
1!
#1180000
0!
#1185000
0)
b100 #
b100 0
b100 (
b11 *
b11 ,
1!
#1190000
0!
#1195000
0)
b101 #
b101 0
b101 (
b100 ,
b100 *
1!
#1200000
0!
#1205000
b1 1
1%
1)
0$
0'
0&
b0 #
b101 0
b0 (
b101 *
b101 ,
1!
#1210000
0!
#1215000
0%
0)
b1 #
b1 (
1$
1'
1&
b1 0
b0 1
b0 *
b1 -
1!
#1220000
0!
#1225000
0)
b10 #
b10 0
b10 (
b0 -
b1 *
b1 ,
1!
#1230000
0!
#1235000
0)
b11 #
b11 0
b11 (
b10 ,
b10 *
1!
#1240000
0!
#1245000
0)
b100 #
b100 0
b100 (
b11 *
b11 ,
1!
#1250000
0!
#1255000
0)
b101 #
b101 0
b101 (
b100 ,
b100 *
1!
#1260000
0!
#1265000
b1 1
1%
1)
0$
0'
0&
b0 #
b101 0
b0 (
b101 *
b101 ,
1!
#1270000
0!
#1275000
0%
0)
b1 #
b1 (
1$
1'
1&
b1 0
b0 1
b0 *
b1 -
1!
#1280000
0!
#1285000
0)
b10 #
b10 0
b10 (
b0 -
b1 *
b1 ,
1!
#1290000
0!
#1295000
0)
b11 #
b11 0
b11 (
b10 ,
b10 *
1!
#1300000
0!
#1305000
0)
b100 #
b100 0
b100 (
b11 *
b11 ,
1!
#1310000
0!
#1315000
0)
b101 #
b101 0
b101 (
b100 ,
b100 *
1!
#1320000
0!
#1325000
b1 1
1%
1)
0$
0'
0&
b0 #
b101 0
b0 (
b101 *
b101 ,
1!
#1330000
0!
#1335000
0%
0)
b1 #
b1 (
1$
1'
1&
b1 0
b0 1
b0 *
b1 -
1!
#1340000
0!
#1345000
0)
b10 #
b10 0
b10 (
b0 -
b1 *
b1 ,
1!
#1350000
0!
#1355000
0)
b11 #
b11 0
b11 (
b10 ,
b10 *
1!
#1360000
0!
#1365000
0)
b100 #
b100 0
b100 (
b11 *
b11 ,
1!
#1370000
0!
#1375000
0)
b101 #
b101 0
b101 (
b100 ,
b100 *
1!
#1380000
0!
#1385000
b1 1
1%
1)
0$
0'
0&
b0 #
b101 0
b0 (
b101 *
b101 ,
1!
#1390000
0!
#1395000
0%
0)
b1 #
b1 (
1$
1'
1&
b1 0
b0 1
b0 *
b1 -
1!
#1400000
0!
#1405000
0)
b10 #
b10 0
b10 (
b0 -
b1 *
b1 ,
1!
#1410000
0!
#1415000
0)
b11 #
b11 0
b11 (
b10 ,
b10 *
1!
#1420000
0!
#1425000
0)
b100 #
b100 0
b100 (
b11 *
b11 ,
1!
#1430000
0!
#1435000
0)
b101 #
b101 0
b101 (
b100 ,
b100 *
1!
#1440000
0!
#1445000
b1 1
1%
1)
0$
0'
0&
b0 #
b101 0
b0 (
b101 *
b101 ,
1!
#1450000
0!
#1455000
0%
0)
b1 #
b1 (
1$
1'
1&
b1 0
b0 1
b0 *
b1 -
1!
#1460000
0!
#1465000
0)
b10 #
b10 0
b10 (
b0 -
b1 *
b1 ,
1!
#1470000
0!
#1475000
0)
b11 #
b11 0
b11 (
b10 ,
b10 *
1!
#1480000
0!
#1485000
0)
b100 #
b100 0
b100 (
b11 *
b11 ,
1!
#1490000
0!
#1495000
0)
b101 #
b101 0
b101 (
b100 ,
b100 *
1!
#1500000
0!
#1505000
b1 1
1%
1)
0$
0'
0&
b0 #
b101 0
b0 (
b101 *
b101 ,
1!
#1510000
0!
#1515000
0%
0)
b1 #
b1 (
1$
1'
1&
b1 0
b0 1
b0 *
b1 -
1!
#1520000
0!
#1525000
0)
b10 #
b10 0
b10 (
b0 -
b1 *
b1 ,
1!
#1530000
0!
#1535000
0)
b11 #
b11 0
b11 (
b10 ,
b10 *
1!
#1540000
0!
#1545000
0)
b100 #
b100 0
b100 (
b11 *
b11 ,
1!
#1550000
0!
#1555000
0)
b101 #
b101 0
b101 (
b100 ,
b100 *
1!
#1560000
0!
#1565000
b1 1
1%
1)
0$
0'
0&
b0 #
b101 0
b0 (
b101 *
b101 ,
1!
#1570000
0!
#1575000
0%
0)
b1 #
b1 (
1$
1'
1&
b1 0
b0 1
b0 *
b1 -
1!
#1580000
0!
#1585000
0)
b10 #
b10 0
b10 (
b0 -
b1 *
b1 ,
1!
#1590000
0!
#1595000
0)
b11 #
b11 0
b11 (
b10 ,
b10 *
1!
#1600000
0!
#1605000
0)
b100 #
b100 0
b100 (
b11 *
b11 ,
1!
#1610000
0!
#1615000
0)
b101 #
b101 0
b101 (
b100 ,
b100 *
1!
#1620000
0!
#1625000
b1 1
1%
1)
0$
0'
0&
b0 #
b101 0
b0 (
b101 *
b101 ,
1!
#1630000
0!
#1635000
0%
0)
b1 #
b1 (
1$
1'
1&
b1 0
b0 1
b0 *
b1 -
1!
#1640000
0!
#1645000
0)
b10 #
b10 0
b10 (
b0 -
b1 *
b1 ,
1!
#1650000
0!
#1655000
0)
b11 #
b11 0
b11 (
b10 ,
b10 *
1!
#1660000
0!
#1665000
0)
b100 #
b100 0
b100 (
b11 *
b11 ,
1!
#1670000
0!
#1675000
0)
b101 #
b101 0
b101 (
b100 ,
b100 *
1!
#1680000
0!
#1685000
b1 1
1%
1)
0$
0'
0&
b0 #
b101 0
b0 (
b101 *
b101 ,
1!
#1690000
0!
#1695000
0%
0)
b1 #
b1 (
1$
1'
1&
b1 0
b0 1
b0 *
b1 -
1!
#1700000
0!
#1705000
0)
b10 #
b10 0
b10 (
b0 -
b1 *
b1 ,
1!
#1710000
0!
#1715000
0)
b11 #
b11 0
b11 (
b10 ,
b10 *
1!
#1720000
0!
#1725000
0)
b100 #
b100 0
b100 (
b11 *
b11 ,
1!
#1730000
0!
#1735000
0)
b101 #
b101 0
b101 (
b100 ,
b100 *
1!
#1740000
0!
#1745000
b1 1
1%
1)
0$
0'
0&
b0 #
b101 0
b0 (
b101 *
b101 ,
1!
#1750000
0!
#1755000
0%
0)
b1 #
b1 (
1$
1'
1&
b1 0
b0 1
b0 *
b1 -
1!
#1760000
0!
#1765000
0)
b10 #
b10 0
b10 (
b0 -
b1 *
b1 ,
1!
#1770000
0!
#1775000
0)
b11 #
b11 0
b11 (
b10 ,
b10 *
1!
#1780000
0!
#1785000
0)
b100 #
b100 0
b100 (
b11 *
b11 ,
1!
#1790000
0!
#1795000
0)
b101 #
b101 0
b101 (
b100 ,
b100 *
1!
#1800000
0!
#1805000
b1 1
1%
1)
0$
0'
0&
b0 #
b101 0
b0 (
b101 *
b101 ,
1!
#1810000
0!
#1815000
0%
0)
b1 #
b1 (
1$
1'
1&
b1 0
b0 1
b0 *
b1 -
1!
#1820000
0!
#1825000
0)
b10 #
b10 0
b10 (
b0 -
b1 *
b1 ,
1!
#1830000
0!
#1835000
0)
b11 #
b11 0
b11 (
b10 ,
b10 *
1!
#1840000
0!
#1845000
0)
b100 #
b100 0
b100 (
b11 *
b11 ,
1!
#1850000
0!
#1855000
0)
b101 #
b101 0
b101 (
b100 ,
b100 *
1!
#1860000
0!
#1865000
b1 1
1%
1)
0$
0'
0&
b0 #
b101 0
b0 (
b101 *
b101 ,
1!
#1870000
0!
#1875000
0%
0)
b1 #
b1 (
1$
1'
1&
b1 0
b0 1
b0 *
b1 -
1!
#1880000
0!
#1885000
0)
b10 #
b10 0
b10 (
b0 -
b1 *
b1 ,
1!
#1890000
0!
#1895000
0)
b11 #
b11 0
b11 (
b10 ,
b10 *
1!
#1900000
0!
#1905000
0)
b100 #
b100 0
b100 (
b11 *
b11 ,
1!
#1910000
0!
#1915000
0)
b101 #
b101 0
b101 (
b100 ,
b100 *
1!
#1920000
0!
#1925000
b1 1
1%
1)
0$
0'
0&
b0 #
b101 0
b0 (
b101 *
b101 ,
1!
#1930000
0!
#1935000
0%
0)
b1 #
b1 (
1$
1'
1&
b1 0
b0 1
b0 *
b1 -
1!
#1940000
0!
#1945000
0)
b10 #
b10 0
b10 (
b0 -
b1 *
b1 ,
1!
#1950000
0!
#1955000
0)
b11 #
b11 0
b11 (
b10 ,
b10 *
1!
#1960000
0!
#1965000
0)
b100 #
b100 0
b100 (
b11 *
b11 ,
1!
#1970000
0!
#1975000
0)
b101 #
b101 0
b101 (
b100 ,
b100 *
1!
#1980000
0!
#1985000
b1 1
1%
1)
0$
0'
0&
b0 #
b101 0
b0 (
b101 *
b101 ,
1!
#1990000
0!
#1995000
0%
0)
b1 #
b1 (
1$
1'
1&
b1 0
b0 1
b0 *
b1 -
1!
#2000000
0!
#2005000
0)
b10 #
b10 0
b10 (
b0 -
b1 *
b1 ,
1!
#2010000
0!
#2015000
0)
b11 #
b11 0
b11 (
b10 ,
b10 *
1!
#2020000
0!
#2025000
0)
b100 #
b100 0
b100 (
b11 *
b11 ,
1!
#2030000
0!
#2035000
0)
b101 #
b101 0
b101 (
b100 ,
b100 *
1!
#2040000
0!
#2045000
b1 1
1%
1)
0$
0'
0&
b0 #
b101 0
b0 (
b101 *
b101 ,
1!
#2050000
0!
#2055000
0%
0)
b1 #
b1 (
1$
1'
1&
b1 0
b0 1
b0 *
b1 -
1!
#2060000
0!
#2065000
0)
b10 #
b10 0
b10 (
b0 -
b1 *
b1 ,
1!
#2070000
0!
#2075000
0)
b11 #
b11 0
b11 (
b10 ,
b10 *
1!
#2080000
0!
#2085000
0)
b100 #
b100 0
b100 (
b11 *
b11 ,
1!
#2090000
0!
#2095000
0)
b101 #
b101 0
b101 (
b100 ,
b100 *
1!
#2100000
0!
#2105000
b1 1
1%
1)
0$
0'
0&
b0 #
b101 0
b0 (
b101 *
b101 ,
1!
#2110000
0!
#2115000
0%
0)
b1 #
b1 (
1$
1'
1&
b1 0
b0 1
b0 *
b1 -
1!
#2120000
0!
#2125000
0)
b10 #
b10 0
b10 (
b0 -
b1 *
b1 ,
1!
#2130000
0!
#2135000
0)
b11 #
b11 0
b11 (
b10 ,
b10 *
1!
#2140000
0!
#2145000
0)
b100 #
b100 0
b100 (
b11 *
b11 ,
1!
#2150000
0!
#2155000
0)
b101 #
b101 0
b101 (
b100 ,
b100 *
1!
#2160000
0!
#2165000
b1 1
1%
1)
0$
0'
0&
b0 #
b101 0
b0 (
b101 *
b101 ,
1!
#2170000
0!
#2175000
0%
0)
b1 #
b1 (
1$
1'
1&
b1 0
b0 1
b0 *
b1 -
1!
#2180000
0!
#2185000
0)
b10 #
b10 0
b10 (
b0 -
b1 *
b1 ,
1!
#2190000
0!
#2195000
0)
b11 #
b11 0
b11 (
b10 ,
b10 *
1!
#2200000
0!
#2205000
0)
b100 #
b100 0
b100 (
b11 *
b11 ,
1!
#2210000
0!
#2215000
0)
b101 #
b101 0
b101 (
b100 ,
b100 *
1!
#2220000
0!
#2225000
b1 1
1%
1)
0$
0'
0&
b0 #
b101 0
b0 (
b101 *
b101 ,
1!
#2230000
0!
#2235000
0%
0)
b1 #
b1 (
1$
1'
1&
b1 0
b0 1
b0 *
b1 -
1!
#2240000
0!
#2245000
0)
b10 #
b10 0
b10 (
b0 -
b1 *
b1 ,
1!
#2250000
0!
#2255000
0)
b11 #
b11 0
b11 (
b10 ,
b10 *
1!
#2260000
0!
#2265000
0)
b100 #
b100 0
b100 (
b11 *
b11 ,
1!
#2270000
0!
#2275000
0)
b101 #
b101 0
b101 (
b100 ,
b100 *
1!
#2280000
0!
#2285000
b1 1
1%
1)
0$
0'
0&
b0 #
b101 0
b0 (
b101 *
b101 ,
1!
#2290000
0!
#2295000
0%
0)
b1 #
b1 (
1$
1'
1&
b1 0
b0 1
b0 *
b1 -
1!
#2300000
0!
#2305000
0)
b10 #
b10 0
b10 (
b0 -
b1 *
b1 ,
1!
#2310000
0!
#2315000
0)
b11 #
b11 0
b11 (
b10 ,
b10 *
1!
#2320000
0!
#2325000
0)
b100 #
b100 0
b100 (
b11 *
b11 ,
1!
#2330000
0!
#2335000
0)
b101 #
b101 0
b101 (
b100 ,
b100 *
1!
#2340000
0!
#2345000
b1 1
1%
1)
0$
0'
0&
b0 #
b101 0
b0 (
b101 *
b101 ,
1!
#2350000
0!
#2355000
0%
0)
b1 #
b1 (
1$
1'
1&
b1 0
b0 1
b0 *
b1 -
1!
#2360000
0!
